arkitema_config/__init__.py
arkitema_config/config.py
arkitema_config/connection.py
arkitema_config/context.py
arkitema_config/email.py
arkitema_config/exceptions.py
arkitema_config/fastapi.py
arkitema_config/formatting.py
arkitema_config/graphql/__init__.py
arkitema_config/graphql/input_filters.py
arkitema_config/graphql/pagination.py
arkitema_config/load_db.py
arkitema_config/monitoring.py
arkitema_config/permissions.py
arkitema_config/router.py
arkitema_config/security.py
arkitema_config/user.py
arkitema_config-0.1.7.dist-info/LICENSE
arkitema_config-0.1.7.dist-info/METADATA
arkitema_config-0.1.7.dist-info/WHEEL
arkitema_config-0.1.7.dist-info/RECORD
