Metadata-Version: 2.1
Name: arkitema-config
Version: 0.1.7
Summary: Configurations for Arkitema FastAPI apps
Home-page: https://github.com/Arkitema/backend-config
License: Apache-2.0
Author: Christian Kongsgaard
Author-email: chrk@arkitema.com
Requires-Python: >=3.11,<4.0
Classifier: License :: OSI Approved :: Apache Software License
Classifier: Programming Language :: Python :: 3
Classifier: Programming Language :: Python :: 3.11
Classifier: Programming Language :: Python :: 3.12
Provides-Extra: database
Requires-Dist: SQLAlchemy[asyncio] (>=1.4.35) ; extra == "database"
Requires-Dist: aiocache
Requires-Dist: asyncpg (>=0.26.0,<0.27.0) ; extra == "database"
Requires-Dist: fastapi-azure-auth (>=4.0.0)
Requires-Dist: msgraph-core
Requires-Dist: opentelemetry-api
Requires-Dist: opentelemetry-exporter-otlp
Requires-Dist: opentelemetry-instrumentation-fastapi
Requires-Dist: opentelemetry-instrumentation-logging
Requires-Dist: opentelemetry-sdk
Requires-Dist: prometheus-client
Requires-Dist: pydantic
Requires-Dist: requests
Requires-Dist: sendgrid
Requires-Dist: sqlmodel (>=0.0.8) ; extra == "database"
Requires-Dist: strawberry-graphql[fastapi] (>=0.164.0)
Project-URL: Repository, https://github.com/Arkitema/backend-config
